ablog/__init__.py
ablog/_version.py
ablog/blog.py
ablog/commands.py
ablog/post.py
ablog/start.py
ablog/version.py
ablog/locales/sphinx.pot
ablog/locales/ca/LC_MESSAGES/sphinx.po
ablog/locales/de/LC_MESSAGES/sphinx.po
ablog/locales/es/LC_MESSAGES/sphinx.po
ablog/locales/et/LC_MESSAGES/sphinx.po
ablog/locales/fr/LC_MESSAGES/sphinx.po
ablog/locales/it/LC_MESSAGES/sphinx.po
ablog/locales/pt/LC_MESSAGES/sphinx.po
ablog/locales/ru/LC_MESSAGES/sphinx.po
ablog/locales/tr/LC_MESSAGES/sphinx.po
ablog/locales/zh_CN/LC_MESSAGES/sphinx.po
ablog/stylesheets/ablog/tagcloud.css
ablog/templates/archives.html
ablog/templates/authors.html
ablog/templates/catalog.html
ablog/templates/categories.html
ablog/templates/collection.html
ablog/templates/languages.html
ablog/templates/locations.html
ablog/templates/page.html
ablog/templates/postcard.html
ablog/templates/postcard2.html
ablog/templates/postnavy.html
ablog/templates/recentposts.html
ablog/templates/redirect.html
ablog/templates/tagcloud.html
ablog/templates/ablog/archives.html
ablog/templates/ablog/authors.html
ablog/templates/ablog/catalog.html
ablog/templates/ablog/categories.html
ablog/templates/ablog/collection.html
ablog/templates/ablog/languages.html
ablog/templates/ablog/locations.html
ablog/templates/ablog/postcard.html
ablog/templates/ablog/postcard2.html
ablog/templates/ablog/postnavy.html
ablog/templates/ablog/recentposts.html
ablog/templates/ablog/redirect.html
ablog/templates/ablog/tagcloud.html
ablog/tests/__init__.py
ablog/tests/test_build.py
ablog/tests/test_canonical.py
ablog/tests/test_external.py
ablog/tests/test_postlist.py
ablog/tests/test_templates.py
ablog-0.11.13.dist-info/licenses/LICENSE.rst
ablog-0.11.13.dist-info/METADATA
ablog-0.11.13.dist-info/WHEEL
ablog-0.11.13.dist-info/entry_points.txt
ablog-0.11.13.dist-info/top_level.txt
ablog-0.11.13.dist-info/RECORD
